granula/__init__.py
granula/config.py
granula/exception.py
granula/factory.py
granula/operator.py
granula/pattern.py
granula/serializer.py
granula/utils.py
granula/dsl/__init__.py
granula/dsl/defaults.py
granula/dsl/exception.py
granula/dsl/finder.py
granula/dsl/parser.py
granula/dsl/resolver.py
granula/dsl/runner.py
granula/dsl/scanner.py
granula/dsl/token.py
granula-2018.2.8.dist-info/DESCRIPTION.rst
granula-2018.2.8.dist-info/METADATA
granula-2018.2.8.dist-info/RECORD
granula-2018.2.8.dist-info/WHEEL
granula-2018.2.8.dist-info/metadata.json
granula-2018.2.8.dist-info/top_level.txt
tests/fixtures/__init__.py
tests/stubs/__init__.py
tests/stubs/operator.py
tests/stubs/pattern.py
tests/stubs/serializer.py
tests/unit/__init__.py
tests/unit/test_config.py
tests/unit/dsl/__init__.py
tests/unit/dsl/test_parser.py
tests/unit/dsl/test_resolver.py
tests/unit/dsl/test_runner.py
tests/unit/dsl/test_scanner.py
tests/unit/operator/__init__.py
tests/unit/operator/test_environment_variable.py
tests/unit/operator/test_reference.py
tests/unit/operator/test_value.py
tests/unit/pattern/__init__.py
tests/unit/pattern/test_environment.py
tests/unit/serializer/__init__.py
tests/unit/serializer/test_json.py
tests/unit/serializer/test_yaml.py
tests/unit/utils/__init__.py
tests/unit/utils/test_argument_count.py
tests/unit/utils/test_find_files.py
tests/unit/utils/test_merge.py
