Metadata-Version: 1.1
Name: granula
Version: 2018.2.8
Summary: Multi-file Configurations for Python Applications
Home-page: https://github.com/chomechome/granula
Author: Vladislav Blinov
Author-email: cunningplan@yandex.ru
License: MIT
Platform: UNKNOWN
Classifier: License :: OSI Approved :: MIT License
Classifier: Programming Language :: Python
Classifier: Programming Language :: Python :: 2.7
Classifier: Programming Language :: Python :: 3
Classifier: Programming Language :: Python :: 3.4
Classifier: Programming Language :: Python :: 3.5
Classifier: Programming Language :: Python :: 3.6
Classifier: Programming Language :: Python :: Implementation :: CPython
